teehr/__init__.py
teehr/const.py
teehr/evaluation/__init__.py
teehr/evaluation/evaluation.py
teehr/evaluation/fetch.py
teehr/evaluation/generate.py
teehr/evaluation/metrics.py
teehr/evaluation/tables/attribute_table.py
teehr/evaluation/tables/base_table.py
teehr/evaluation/tables/configuration_table.py
teehr/evaluation/tables/domain_table.py
teehr/evaluation/tables/joined_timeseries_table.py
teehr/evaluation/tables/location_attribute_table.py
teehr/evaluation/tables/location_crosswalk_table.py
teehr/evaluation/tables/location_table.py
teehr/evaluation/tables/primary_timeseries_table.py
teehr/evaluation/tables/secondary_timeseries_table.py
teehr/evaluation/tables/timeseries_table.py
teehr/evaluation/tables/unit_table.py
teehr/evaluation/tables/variable_table.py
teehr/evaluation/utils.py
teehr/example_data/__init__.py
teehr/example_data/ensemble_example_data.py
teehr/example_data/nwm_gridded_example_data.py
teehr/example_data/nwm_streamflow_example_data.py
teehr/example_data/two_locations.py
teehr/example_data/v0_3_test_study.py
teehr/examples/01-evaluation_setup.ipynb
teehr/examples/02-table_queries.ipynb
teehr/examples/03-metric_queries.ipynb
teehr/examples/04-table_filters.ipynb
teehr/examples/05-2_site_setup.ipynb
teehr/examples/06-2_site_query.ipynb
teehr/examples/07-2_site_plotting.ipynb
teehr/examples/08-sql.ipynb
teehr/examples/09-ensemble_metric_queries.ipynb
teehr/examples/__init__.py
teehr/examples/clone_from_s3.ipynb
teehr/examples/load_netcdf.ipynb
teehr/examples/ngen_example.py
teehr/examples/partition_by_reference_time.py
teehr/examples/setup_ensemble_example.py
teehr/examples/setup_evaluation.py
teehr/examples/setup_nwm_grid_example.py
teehr/examples/setup_nwm_streamflow_example.py
teehr/examples/two_site_debug_script.py
teehr/fetching/__init__.py
teehr/fetching/const.py
teehr/fetching/nwm/__init__.py
teehr/fetching/nwm/grid_utils.py
teehr/fetching/nwm/nwm_grids.py
teehr/fetching/nwm/nwm_points.py
teehr/fetching/nwm/point_utils.py
teehr-0.5.3.dist-info/METADATA
teehr-0.5.3.dist-info/WHEEL
teehr-0.5.3.dist-info/licenses/LICENSE.md
teehr-0.5.3.dist-info/RECORD
