Metadata-Version: 2.4
Name: teehr
Version: 0.5.3
Summary: Tools for Exploratory Evaluation in Hydrologic Research
License: GNU v3
License-File: LICENSE.md
Author: RTI International
Requires-Python: >=3.10,<3.14
Classifier: License :: Other/Proprietary License
Classifier: Programming Language :: Python :: 3
Classifier: Programming Language :: Python :: 3.10
Classifier: Programming Language :: Python :: 3.11
Classifier: Programming Language :: Python :: 3.12
Classifier: Programming Language :: Python :: 3.13
Requires-Dist: apache-sedona (>=1.7.0,<2)
Requires-Dist: arch (>=7.0.0,<8)
Requires-Dist: baseflow (>=0.1.0,<0.2.0)
Requires-Dist: bokeh (>=3.7.3,<4)
Requires-Dist: dask (>=2025,<2026)
Requires-Dist: dataretrieval (>=1.0.9,<2)
Requires-Dist: fsspec (>=2023.10.0,<2026)
Requires-Dist: gcsfs (>=2023.10.0,<2026)
Requires-Dist: geopandas (>=1,<2)
Requires-Dist: h5py (>=3.12.1,<4)
Requires-Dist: httpx (>=0.25.1,<1)
Requires-Dist: kerchunk (>=0.2.2,<1)
Requires-Dist: lxml (>=5.4.0,<6)
Requires-Dist: netcdf4 (>=1.6.5,<2)
Requires-Dist: numba (>=0.60.0,<1)
Requires-Dist: pandas (>=2.2.0,<3)
Requires-Dist: pandera[pyspark] (>=0.20.4,<1)
Requires-Dist: protobuf (==5.28.3)
Requires-Dist: psutil (>=7.0.0,<8)
Requires-Dist: pyarrow (>=15.0.0,<21)
Requires-Dist: pydantic (>=2.4.2,<3)
Requires-Dist: pyiceberg (>=0.9.1,<1)
Requires-Dist: pyspark[pandas-on-spark] (==4.0.1)
Requires-Dist: rasterio (>=1.3.0,<2)
Requires-Dist: rioxarray (>=0.15.0,<1)
Requires-Dist: s3fs (>=2023.10.0,<2026)
Requires-Dist: scoringrules (>=0.7.1,<1)
Requires-Dist: ujson (>=5.8.0,<6)
Requires-Dist: zarr (>=2.16.1,<3)
